ptwebdiscover/__init__.py
ptwebdiscover/_version.py
ptwebdiscover/backups.py
ptwebdiscover/counters.py
ptwebdiscover/findings.py
ptwebdiscover/helpers.py
ptwebdiscover/ptwebdiscover.py
ptwebdiscover/responseprocessor.py
ptwebdiscover/results.py
ptwebdiscover/scanner.py
ptwebdiscover/sitemap.py
ptwebdiscover/target.py
ptwebdiscover/webarchive.py
ptwebdiscover/ptdataclasses/__init__.py
ptwebdiscover/ptdataclasses/argumentoptions.py
ptwebdiscover/ptdataclasses/findingdetail.py
ptwebdiscover/utils/__init__.py
ptwebdiscover/utils/args_processing.py
ptwebdiscover/utils/treeshow.py
ptwebdiscover/utils/url.py
ptwebdiscover/utils/__pycache__/__init__.cpython-313.pyc
ptwebdiscover/utils/__pycache__/cachefile.cpython-313.pyc
ptwebdiscover/utils/__pycache__/robots_txt_parser.cpython-313.pyc
ptwebdiscover/utils/__pycache__/treeshow.cpython-313.pyc
ptwebdiscover/utils/__pycache__/url.cpython-313.pyc
ptwebdiscover/utils/__pycache__/web_archive.cpython-313.pyc
ptwebdiscover-1.1.3.dist-info/licenses/LICENSE
ptwebdiscover-1.1.3.dist-info/METADATA
ptwebdiscover-1.1.3.dist-info/WHEEL
ptwebdiscover-1.1.3.dist-info/entry_points.txt
ptwebdiscover-1.1.3.dist-info/top_level.txt
ptwebdiscover-1.1.3.dist-info/RECORD
